pony-stubs/METADATA.toml
pony-stubs/__init__.pyi
pony-stubs/converting.pyi
pony-stubs/options.pyi
pony-stubs/py.typed
pony-stubs/py23compat.pyi
pony-stubs/flask/__init__.pyi
pony-stubs/flask/example/__init__.pyi
pony-stubs/flask/example/app.pyi
pony-stubs/flask/example/config.pyi
pony-stubs/flask/example/models.pyi
pony-stubs/flask/example/views.pyi
pony-stubs/orm/__init__.pyi
pony-stubs/orm/asttranslation.pyi
pony-stubs/orm/core.pyi
pony-stubs/orm/dbapiprovider.pyi
pony-stubs/orm/dbschema.pyi
pony-stubs/orm/decompiling.pyi
pony-stubs/orm/ormtypes.pyi
pony-stubs/orm/serialization.pyi
pony-stubs/orm/sqlbuilding.pyi
pony-stubs/orm/sqlsymbols.pyi
pony-stubs/orm/sqltranslation.pyi
pony-stubs/orm/dbproviders/__init__.pyi
pony-stubs/orm/dbproviders/cockroach.pyi
pony-stubs/orm/dbproviders/mysql.pyi
pony-stubs/orm/dbproviders/oracle.pyi
pony-stubs/orm/dbproviders/postgres.pyi
pony-stubs/orm/dbproviders/sqlite.pyi
pony-stubs/orm/examples/__init__.pyi
pony-stubs/orm/examples/alessandro_bug.pyi
pony-stubs/orm/examples/bottle_example.pyi
pony-stubs/orm/examples/bug_ben.pyi
pony-stubs/orm/examples/compositekeys.pyi
pony-stubs/orm/examples/demo.pyi
pony-stubs/orm/examples/estore.pyi
pony-stubs/orm/examples/inheritance1.pyi
pony-stubs/orm/examples/numbers.pyi
pony-stubs/orm/examples/session01.pyi
pony-stubs/orm/examples/university1.pyi
pony-stubs/orm/examples/university2.pyi
pony-stubs/orm/integration/__init__.pyi
pony-stubs/orm/integration/bottle_plugin.pyi
pony-stubs/thirdparty/__init__.pyi
pony-stubs/thirdparty/decorator.pyi
pony-stubs/utils/__init__.pyi
pony-stubs/utils/properties.pyi
pony-stubs/utils/utils.pyi
types_pony-0.7.0.20250822.dist-info/licenses/LICENSE
types_pony-0.7.0.20250822.dist-info/METADATA
types_pony-0.7.0.20250822.dist-info/WHEEL
types_pony-0.7.0.20250822.dist-info/top_level.txt
types_pony-0.7.0.20250822.dist-info/RECORD
